mypackage/__init__.py
mypackage/main.py
Helloworld2023-0.0.3.dist-info/METADATA
Helloworld2023-0.0.3.dist-info/WHEEL
Helloworld2023-0.0.3.dist-info/top_level.txt
Helloworld2023-0.0.3.dist-info/RECORD
