Metadata-Version: 2.1
Name: Helloworld2023
Version: 0.0.3
Summary: A small example package
Home-page: https://github.com/BhuvaneshwaraRagavendra/Hello-World
Author: Bhuvaneshwaran
Author-email: Bhuvaneshwararagavendra@gmail.com
Project-URL: Bug Tracker, https://github.com/BhuvaneshwaraRagavendra/Hello-World/issues
Classifier: Programming Language :: Python :: 3
Classifier: License :: OSI Approved :: MIT License
Classifier: Operating System :: OS Independent
Requires-Python: >=3.6
